openedx_certificates/__init__.py
openedx_certificates/admin.py
openedx_certificates/apps.py
openedx_certificates/compat.py
openedx_certificates/exceptions.py
openedx_certificates/generators.py
openedx_certificates/models.py
openedx_certificates/processors.py
openedx_certificates/tasks.py
openedx_certificates/urls.py
openedx_certificates/views.py
openedx_certificates/migrations/0001_initial.py
openedx_certificates/migrations/__init__.py
openedx_certificates/settings/__init__.py
openedx_certificates/settings/common.py
openedx_certificates/settings/production.py
openedx_certificates/templates/openedx_certificates/base.html
openedx_certificates/templates/openedx_certificates/edx_ace/certificate_generated/email/body.html
openedx_certificates/templates/openedx_certificates/edx_ace/certificate_generated/email/head.html
openedx_certificates-0.1.0.dist-info/LICENSE.txt
openedx_certificates-0.1.0.dist-info/METADATA
openedx_certificates-0.1.0.dist-info/WHEEL
openedx_certificates-0.1.0.dist-info/entry_points.txt
openedx_certificates-0.1.0.dist-info/top_level.txt
openedx_certificates-0.1.0.dist-info/RECORD
