Metadata-Version: 2.2
Name: openedx-certificates
Version: 0.1.0
Summary: A pluggable service for preparing Open edX certificates.
Home-page: https://github.com/open-craft/openedx-certificates
Author: OpenCraft
Author-email: help@opencraft.com
License: AGPL 3.0
Keywords: Python edx
Classifier: Development Status :: 3 - Alpha
Classifier: Framework :: Django
Classifier: Framework :: Django :: 4.2
Classifier: Intended Audience :: Developers
Classifier: License :: OSI Approved :: GNU Affero General Public License v3 or later (AGPLv3+)
Classifier: Natural Language :: English
Classifier: Programming Language :: Python :: 3
Classifier: Programming Language :: Python :: 3.11
Classifier: Programming Language :: Python :: 3.12
Requires-Python: >=3.11
License-File: LICENSE.txt
Requires-Dist: celery
Requires-Dist: django
Requires-Dist: django-celery-beat
Requires-Dist: django-model-utils
Requires-Dist: django-object-actions
Requires-Dist: django_reverse_admin
Requires-Dist: djangorestframework
Requires-Dist: edx-opaque-keys
Requires-Dist: edx_ace
Requires-Dist: openedx-completion-aggregator
Requires-Dist: pypdf
Requires-Dist: reportlab
Dynamic: author
Dynamic: author-email
Dynamic: classifier
Dynamic: description
Dynamic: description-content-type
Dynamic: home-page
Dynamic: keywords
Dynamic: license
Dynamic: requires-dist
Dynamic: requires-python
Dynamic: summary
